pyroscope/__init__.py
pyroscope/_native.py
pyroscope/_native__ffi.py
pyroscope/_native__lib.cpython-311-darwin.so
pyroscope_io/__init__.py
pyroscope_io-0.8.16.dist-info/LICENSE
pyroscope_io-0.8.16.dist-info/METADATA
pyroscope_io-0.8.16.dist-info/WHEEL
pyroscope_io-0.8.16.dist-info/top_level.txt
pyroscope_io-0.8.16.dist-info/RECORD
