Metadata-Version: 2.1
Name: pyroscope-io
Version: 0.8.16
Summary: Pyroscope Python integration
Home-page: https://pyroscope.io
Maintainer: Abid Omar
Maintainer-email: contact@pyroscope.io
License: Apache 2.0
Project-URL: Documentation, https://pyroscope.io
Project-URL: Bug Tracker, https://pyroscope.io
Project-URL: Discussions, https://pyroscope.io
Project-URL: Changelog, https://pyroscope.io
Platform: any
Classifier: Intended Audience :: Developers
Classifier: License :: OSI Approved :: Apache Software License
Classifier: Operating System :: MacOS
Classifier: Operating System :: POSIX
Classifier: Operating System :: Unix
Classifier: Programming Language :: Python
Classifier: Topic :: Software Development
Classifier: Topic :: Software Development :: Debuggers
Classifier: Topic :: Utilities
License-File: LICENSE
Requires-Dist: cffi>=1.6.0
